bids_explorer/__init__.py
bids_explorer/architecture/__init__.py
bids_explorer/architecture/architecture.py
bids_explorer/architecture/mixins.py
bids_explorer/architecture/validation.py
bids_explorer/elements/electrodes.py
bids_explorer/paths/base.py
bids_explorer/paths/bids.py
bids_explorer/paths/query.py
bids_explorer/utils/__init__.py
bids_explorer/utils/database.py
bids_explorer/utils/errors.py
bids_explorer/utils/parsing.py
bids_explorer-0.1.0.dist-info/LICENSE
bids_explorer-0.1.0.dist-info/METADATA
bids_explorer-0.1.0.dist-info/WHEEL
bids_explorer-0.1.0.dist-info/RECORD
