Metadata-Version: 2.3
Name: bids_explorer
Version: 0.1.0
Summary: A simple bids dataset explorer without being too strict
Home-page: https://sam54000.github.io/bids_explorer/bids_explorer.html
License: GPL-3.0-or-later
Keywords: bids,neuroimaging,eeg,dataset,explorer,neuroscience
Author: Dr. Samuel Louviot
Author-email: sam.louviot@gmail.com
Requires-Python: >=3.11,<4.0
Classifier: Intended Audience :: Science/Research
Classifier: License :: OSI Approved :: GNU General Public License v3 or later (GPLv3+)
Classifier: Natural Language :: English
Classifier: Operating System :: OS Independent
Classifier: Programming Language :: Python :: 3
Classifier: Programming Language :: Python :: 3.11
Classifier: Programming Language :: Python :: 3.12
Classifier: Programming Language :: Python :: 3.13
Classifier: Topic :: Scientific/Engineering :: Medical Science Apps.
Requires-Dist: numpy (>=1.26.0,<2.0.0)
Requires-Dist: pandas (>=2.1.0,<3.0.0)
Project-URL: Documentation, https://sam54000.github.io/bids_explorer/bids_explorer.html
Project-URL: Repository, https://github.com/Sam54000/bids_explorer
